simple_encryptor/__init__.py
simple_encryptor/main.py
simple_encryptor-0.2.3.dist-info/LICENSE
simple_encryptor-0.2.3.dist-info/METADATA
simple_encryptor-0.2.3.dist-info/WHEEL
simple_encryptor-0.2.3.dist-info/top_level.txt
simple_encryptor-0.2.3.dist-info/RECORD
